batconf/__init__.py
batconf/manager.py
batconf/py.typed
batconf/source.py
batconf/sources/__init__.py
batconf/sources/argparse.py
batconf/sources/args.py
batconf/sources/dataclass.py
batconf/sources/env.py
batconf/sources/file.py
batconf/sources/ini.py
batconf/sources/toml.py
batconf/sources/yaml.py
batconf/sources/tests/__init__.py
batconf/sources/tests/argparse_test.py
batconf/sources/tests/args_test.py
batconf/sources/tests/dataclass_test.py
batconf/sources/tests/env_test.py
batconf/sources/tests/file_test.py
batconf/sources/tests/ini_test.py
batconf/sources/tests/toml_test.py
batconf/sources/tests/yaml_test.py
batconf/tests/__init__.py
batconf/tests/manager_test.py
batconf/tests/source_test.py
batconf-0.3.1.dist-info/METADATA
batconf-0.3.1.dist-info/WHEEL
batconf-0.3.1.dist-info/licenses/LICENSE
batconf-0.3.1.dist-info/RECORD
