Metadata-Version: 2.4
Name: batconf
Version: 0.3.1
Summary: Application configuration tool from the BAT project
Project-URL: documentation, https://batconf.readthedocs.io/en/latest/
Project-URL: repository, https://github.com/lundybernard/batconf/
Project-URL: issues, https://github.com/lundybernard/batconf/issues
Project-URL: changelog, https://batconf.readthedocs.io/en/latest/changelog.html
Author-email: Lundy Bernard <lundy.bernard@gmail.com>, Lauren Moore <donotreply@no.com>
License: MIT License
License-File: LICENSE
Classifier: Development Status :: 4 - Beta
Classifier: Intended Audience :: Developers
Classifier: Operating System :: MacOS
Classifier: Operating System :: Microsoft :: Windows
Classifier: Operating System :: OS Independent
Classifier: Operating System :: POSIX :: Linux
Classifier: Programming Language :: Python :: 3
Classifier: Programming Language :: Python :: 3 :: Only
Classifier: Programming Language :: Python :: 3.10
Classifier: Programming Language :: Python :: 3.11
Classifier: Programming Language :: Python :: 3.12
Classifier: Programming Language :: Python :: 3.13
Classifier: Programming Language :: Python :: 3.14
Classifier: Programming Language :: Python :: Free Threading
Requires-Python: >=3.10
Provides-Extra: toml
Requires-Dist: toml; (python_version <= '3.10') and extra == 'toml'
Provides-Extra: yaml
Requires-Dist: pyyaml; extra == 'yaml'
